uart_vd_sim/uart_vd.v
`timescale 1ns / 1ps
`define clk_period  20

module uart_vd(
    input rx_i,
    output reg tx_o
);

//-------------------------------------------------------------------------------    
reg [7:0] rx_data;
reg [7:0] tx_data;

reg start_bit, stop_bit, rx_done;
//-------------------------------------------------------------------------------
initial
begin
    tx_o = 1;    
    rx_done = 0;
    start_bit = 0;

    rx_data = 8'h00;    
    tx_data = 8'h55;     

    #(`clk_period * 10); 
    tx_task;
end       

//----------------------------------------------------------------------
task tx_task;
    begin
            tx_o = 0;              
            #(`clk_period * 10);      //start bit;

            tx_o = tx_data[0];          //bit 0;
            #(`clk_period * 10);    

            tx_o = tx_data[1];          //bit 1;
            #(`clk_period * 10);       

            tx_o = tx_data[2];          //bit 2;  
            #(`clk_period * 10);    

            tx_o = tx_data[3];          //bit 3;
            #(`clk_period * 10);     

            tx_o = tx_data[4];          //bit 4;
            #(`clk_period * 10);        

            tx_o = tx_data[5];          //bit 5;
            #(`clk_period * 10);           

            tx_o = tx_data[6];          //bit 6;
            #(`clk_period * 10);            

            tx_o = tx_data[7];          //bit 7;
            #(`clk_period * 10);            

            tx_o = 1;                   //stop bit;
            #(`clk_period * 10);         

            tx_o = 1; 
    end
endtask    

//-------------------------------------------------------------------------------    
always @(negedge rx_i)
    begin
        rx_done = 0;
        rx_data = 8'h00;

        #(`clk_period * 5) start_bit = rx_i;
        if ( start_bit == 0 )
        begin
            #(`clk_period * 10);     rx_data[0] = rx_i;
            #(`clk_period * 10);     rx_data[1] = rx_i;
            #(`clk_period * 10);     rx_data[2] = rx_i;
            #(`clk_period * 10);     rx_data[3] = rx_i;
            #(`clk_period * 10);     rx_data[4] = rx_i;
            #(`clk_period * 10);     rx_data[5] = rx_i;       
            #(`clk_period * 10);     rx_data[6] = rx_i;
            #(`clk_period * 10);     rx_data[7] = rx_i;  
            #(`clk_period * 10);     stop_bit   = rx_i;     
            #(`clk_period * 10);     
            if ( stop_bit == 1 )
            begin
                rx_done = 1;
            end else begin
                rx_done = 0;
            end                    
        end
    end   

//-------------------------------------------------------------------------------    
endmodule

uart_vd/uart_tx.v
`timescale 1ns / 1ps

module uart_tx(
    input clk,
    input rst_n,
    input en_i,
    input [7:0] data_i,
    output reg tx_o,    
    output reg tx_done_o
);

//-------------------------------------------------------------------------------
localparam  s_idle   = 5'b00001,
            s_start  = 5'b00010,
            s_wr     = 5'b00100,
            s_stop   = 5'b01000,
            s_done   = 5'b10000;    
            
//localparam  BPS_CNT =   CLK_FREQUENCE/BAUD_RATE-1,     (50_000_000 / 9600) - 1 = 5207;          
 //localparam t_1_bit = 16'd5207;   

//This is for simulation;
localparam t_1_bit = 9;      //from 0 to 9, it is 10; 
        
reg en_cnt;
reg [15:0] cnt;
reg [4:0] state;
reg [7:0] data_r;
reg [7:0] tx_bits;
        
//-------------------------------------------------------------------------------        
always @(posedge clk or negedge rst_n)
    if (!rst_n)
        cnt <= 16'd0;
    else if ((en_cnt == 0) || (cnt == t_1_bit))
        cnt <= 16'd0;
    else
        cnt <= cnt + 16'd1; 

//-------------------------------------------------------------------------------       
always @(posedge clk or negedge rst_n)
    if (!rst_n) begin
        state   <= s_idle;         
        tx_o    <= 1'b1;
        data_r  <= 8'd0;
        en_cnt  <= 1'b0;   
        tx_bits <= 8'd0;        
        tx_done_o <= 1'b0;
    end else begin
        case(state)
            s_idle: 
                begin
                    data_r    <= data_i;                  
                    tx_bits   <= 8'b0;                           
                    tx_done_o <= 1'b0;  

                    if (en_i == 1) begin   
                        en_cnt <= 1'b1;     
                        state  <= s_start;                         
                    end else begin 
                        en_cnt <= 1'b0;  
                        state  <= s_idle;  
                    end                    
                end
                            
            s_start:
                if (cnt == t_1_bit) begin 
                    state <= s_wr;  
                end else begin 
                    tx_o  <= 0;                            
                    state  <= s_start;  
                end       
                    
            s_wr:   
                if (cnt == t_1_bit) begin 
                    if (tx_bits == 8'd7)
                        state <= s_stop; 
                    else begin
                        tx_bits <= tx_bits + 8'd1;
                        state <= s_wr;
                    end
                end else begin  
                    tx_o  <= data_r[tx_bits];                
                    state <= s_wr;
                end    
                        
            s_stop: 
                if (cnt == t_1_bit) begin             
                    state <= s_done; 
                end else begin 
                    tx_o  <= 1'b1;
                    state <= s_stop;  
                end        
                        
            s_done: 
                begin
                    en_cnt    <= 1'b0;
                    tx_done_o <= 1'b1;
                    state     <= s_idle;                     
                end                                                                                                                                                
                            
            default: state <= s_idle;
        endcase  
end        

//-------------------------------------------------------------------------------
endmodule

uart_rx/uart_rx.v
`timescale 1ns / 1ps

module uart_rx(
    input clk,
    input rst_n,
    input rx_i,
    output reg [7:0] data_o,
    output reg rx_done_o
);

//-------------------------------------------------------------------------------
localparam s_idle   = 5'b00001,
           s_start  = 5'b00010,
           s_rd     = 5'b00100,
           s_stop   = 5'b01000,
           s_done   = 5'b10000;           
           
//localparam  BPS_CNT = CLK_FREQUENCE/BAUD_RATE-1,  (50_000_000 / 9600) - 1 = 5207;             
 localparam t_1_bit = 5207;      //16'd5207;  
 localparam t_half_1_bit = 2603; //16'd2603;         

//This is for simulation;
//localparam t_1_bit = 9;      //from 0 to 9, it is 10; 
//localparam t_half_1_bit = 4; //from 0 to 4, it is 5;  
     
//-------------------------------------------------------------------------------     
reg en_cnt;
reg [15:0] cnt;
reg [4:0] state;
reg [7:0] rx_bits;

//-------------------------------------------------------------------------------    
always @(posedge clk or negedge rst_n)
    if (!rst_n)
        cnt <= 16'd0;
    else if ((en_cnt == 0) || (cnt == t_1_bit))
        cnt <= 16'd0;
    else
        cnt <= cnt + 16'd1;

//-------------------------------------------------------------------------------  
reg rx_0, rx_1, rx_2, rx_3;

//-------------------------------------------------------------------------------  
always @(posedge clk or negedge rst_n)
	if (!rst_n) begin
		rx_0 <= 1'b0;
		rx_1 <= 1'b0;	
		rx_2 <= 1'b0;
		rx_3 <= 1'b0;        
    end else begin
		rx_3 <= rx_i;
		rx_2 <= rx_3;	
		rx_1 <= rx_2;
		rx_0 <= rx_1;	        
	end       

//-------------------------------------------------------------------------------  
wire start_flag;
assign start_flag = rx_0 & rx_1 & (~rx_2) & (~rx_3);   //detect the negedge;

//-------------------------------------------------------------------------------
always @(posedge clk or negedge rst_n)
    if (!rst_n) begin
        state      <= s_idle;
        en_cnt     <= 1'b0;
        data_o     <= 8'd0;   
        rx_bits    <= 8'd0;             
        rx_done_o  <= 1'b0;
    end else begin
        case(state)
            s_idle:     
                begin
                    rx_bits   <= 8'd0;  
                    rx_done_o <= 1'b0;                                      

                    if (start_flag) begin     //detect the negedge;   
                        en_cnt <= 1'b1;                                               
                        state  <= s_start; 
                    end else begin 
                        en_cnt <= 1'b0;
                        state  <= s_idle;  
                    end
                end

            s_start:   
                if (cnt == t_half_1_bit) 
                    if (rx_i == 1'b0)
                        state <= s_rd;              //this is the valid start signal. 
                    else
                        state <= s_idle;               //this is the invalid start signal. 
       
            s_rd:       
                if (cnt == t_half_1_bit) 
                    if (rx_bits == 8'd7)
                        state <= s_stop; 
                    else begin
                        data_o[rx_bits] <= rx_i;
                        rx_bits <= rx_bits + 8'd1;
                        state <= s_rd;
                    end

            s_stop:     
                if (cnt == t_half_1_bit)       
                    if (rx_i == 1) 
                        state <= s_done;                             
                    else     
                        state <= s_idle;                  

            s_done:     
                begin 
                    en_cnt    <= 1'b0;
                    rx_done_o <= 1'b1;
                    state     <= s_idle;  
                end                                                                                                                                                
                            
            default: state <= s_idle;
        endcase  
end        
   
//-------------------------------------------------------------------------------   
endmodule

uart_vd/uart_top.v
`timescale 1ns / 1ps

module uart_top(
    input clk,
    input rst_n,
    input rx_i,    
    output tx_o
);

//-------------------------------------------------------------------------------
wire tx_en;
wire [7:0] tx_data;
        
//-------------------------------------------------------------------------------        
uart_rx UART_RX(
    .clk(clk),
    .rst_n(rst_n),
    .rx_i(rx_i),
    .data_o(tx_data),
    .rx_done_o(tx_en)
);

//-------------------------------------------------------------------------------       
uart_tx UART_TX(
    .clk(clk),
    .rst_n(rst_n),
    .en_i(tx_en),
    .data_i(tx_data),
    .tx_o(tx_o),    
    .tx_done_o()
);   

//-------------------------------------------------------------------------------
endmodule

uart_vd/uart_vd_tb.v
`timescale 1ns / 1ps
`define clk_period  20

module uart_vd_tb();

//-------------------------------------------------------------------------------
reg clk, rst_n;
wire rx, tx;

//-------------------------------------------------------------------------------
uart_top UART_TOP(
    .clk(clk),
    .rst_n(rst_n),
    .rx_i(tx),    
    .tx_o(rx)
);
//-------------------------------------------------------------------------------    
uart_vd UART_VD(
    .rx_i(rx),
    .tx_o(tx)
);
//-------------------------------------------------------------------------------    
initial clk = 1;
    always #(`clk_period/2) clk = ~clk;   

//-------------------------------------------------------------------------------
initial begin
    rst_n = 1; 
    #`clk_period;
    
    rst_n = 0;       //begin to reset;
    #`clk_period;    
    
    rst_n = 1;    
    #(`clk_period);       
     
    #(`clk_period * 250);               
    $stop;
end  

//waveform generation
initial
begin
$dumpfile("uart_vd.vcd");
$dumpvars(1);
end
//-------------------------------------------------------------------------------    

endmodule

uart_vd/uart_vd_tb.vcd
$date
	Sat Dec 17 14:36:28 2022
$end
$version
	Icarus Verilog
$end
$timescale
	1ps
$end
$scope module uart_vd_tb $end
$var wire 1 ! tx $end
$var wire 1 " rx $end
$var reg 1 # clk $end
$var reg 1 $ rst_n $end
$scope module UART_TOP $end
$var wire 1 # clk $end
$var wire 1 $ rst_n $end
$var wire 1 " tx_o $end
$var wire 1 % tx_en $end
$var wire 8 & tx_data [7:0] $end
$var wire 1 ! rx_i $end
$scope module UART_RX $end
$var wire 1 # clk $end
$var wire 1 $ rst_n $end
$var wire 1 ' start_flag $end
$var wire 1 ! rx_i $end
$var parameter 5 ( s_done $end
$var parameter 5 ) s_idle $end
$var parameter 5 * s_rd $end
$var parameter 5 + s_start $end
$var parameter 5 , s_stop $end
$var parameter 32 - t_1_bit $end
$var parameter 32 . t_half_1_bit $end
$var reg 16 / cnt [15:0] $end
$var reg 8 0 data_o [7:0] $end
$var reg 1 1 en_cnt $end
$var reg 1 2 rx_0 $end
$var reg 1 3 rx_1 $end
$var reg 1 4 rx_2 $end
$var reg 1 5 rx_3 $end
$var reg 8 6 rx_bits [7:0] $end
$var reg 1 % rx_done_o $end
$var reg 5 7 state [4:0] $end
$upscope $end
$scope module UART_TX $end
$var wire 1 # clk $end
$var wire 8 8 data_i [7:0] $end
$var wire 1 % en_i $end
$var wire 1 $ rst_n $end
$var parameter 5 9 s_done $end
$var parameter 5 : s_idle $end
$var parameter 5 ; s_start $end
$var parameter 5 < s_stop $end
$var parameter 5 = s_wr $end
$var parameter 32 > t_1_bit $end
$var reg 16 ? cnt [15:0] $end
$var reg 8 @ data_r [7:0] $end
$var reg 1 A en_cnt $end
$var reg 5 B state [4:0] $end
$var reg 8 C tx_bits [7:0] $end
$var reg 1 D tx_done_o $end
$var reg 1 " tx_o $end
$upscope $end
$upscope $end
$scope module UART_VD $end
$var wire 1 " rx_i $end
$var reg 8 E rx_data [7:0] $end
$var reg 1 F rx_done $end
$var reg 1 G start_bit $end
$var reg 1 H stop_bit $end
$var reg 8 I tx_data [7:0] $end
$var reg 1 ! tx_o $end
$scope task tx_task $end
$upscope $end
$upscope $end
$upscope $end
$enddefinitions $end
$comment Show the parameter values. $end
$dumpall
b1001 >
b100 =
b1000 <
b10 ;
b1 :
b10000 9
b100 .
b1001 -
b1000 ,
b10 +
b100 *
b1 )
b10000 (
$end
#0
$dumpvars
b1010101 I
xH
0G
0F
b0 E
xD
bx C
b1 B
xA
bx @
bx ?
bx 8
b1 7
bx 6
15
x4
x3
x2
x1
bx 0
bx /
0'
bx &
x%
1$
1#
x"
1!
$end
#10000
0#
#20000
0D
b0 C
0A
b0 @
1"
b0 ?
0%
b0 6
b0 &
b0 0
b0 8
01
05
04
03
02
b0 /
1#
0$
#30000
0#
#40000
15
1#
1$
#50000
0#
#60000
14
1#
#70000
0#
#80000
13
1#
#90000
0#
#100000
12
1#
#110000
0#
#120000
1#
#130000
0#
#140000
1#
#150000
0#
#160000
1#
#170000
0#
#180000
1#
#190000
0#
#200000
05
1#
0!
#210000
0#
#220000
1'
04
1#
#230000
0#
#240000
0'
03
b10 7
11
1#
#250000
0#
#260000
02
b1 /
1#
#270000
0#
#280000
b10 /
1#
#290000
0#
#300000
b11 /
1#
#310000
0#
#320000
b100 /
1#
#330000
0#
#340000
b100 7
b101 /
1#
#350000
0#
#360000
b110 /
1#
#370000
0#
#380000
b111 /
1#
#390000
0#
#400000
b1000 /
15
1#
1!
#410000
0#
#420000
14
b1001 /
1#
#430000
0#
#440000
b0 /
13
1#
#450000
0#
#460000
12
b1 /
1#
#470000
0#
#480000
b10 /
1#
#490000
0#
#500000
b11 /
1#
#510000
0#
#520000
b100 /
1#
#530000
0#
#540000
b1 6
b1 &
b1 0
b1 8
b101 /
1#
#550000
0#
#560000
b110 /
b1 @
1#
#570000
0#
#580000
b111 /
1#
#590000
0#
#600000
b1000 /
05
1#
0!
#610000
0#
#620000
1'
04
b1001 /
1#
#630000
0#
#640000
0'
b0 /
03
1#
#650000
0#
#660000
02
b1 /
1#
#670000
0#
#680000
b10 /
1#
#690000
0#
#700000
b11 /
1#
#710000
0#
#720000
b100 /
1#
#730000
0#
#740000
b10 6
b101 /
1#
#750000
0#
#760000
b110 /
1#
#770000
0#
#780000
b111 /
1#
#790000
0#
#800000
b1000 /
15
1#
1!
#810000
0#
#820000
14
b1001 /
1#
#830000
0#
#840000
b0 /
13
1#
#850000
0#
#860000
12
b1 /
1#
#870000
0#
#880000
b10 /
1#
#890000
0#
#900000
b11 /
1#
#910000
0#
#920000
b100 /
1#
#930000
0#
#940000
b11 6
b101 &
b101 0
b101 8
b101 /
1#
#950000
0#
#960000
b110 /
b101 @
1#
#970000
0#
#980000
b111 /
1#
#990000
0#
#1000000
b1000 /
05
1#
0!
#1010000
0#
#1020000
1'
04
b1001 /
1#
#1030000
0#
#1040000
0'
b0 /
03
1#
#1050000
0#
#1060000
02
b1 /
1#
#1070000
0#
#1080000
b10 /
1#
#1090000
0#
#1100000
b11 /
1#
#1110000
0#
#1120000
b100 /
1#
#1130000
0#
#1140000
b100 6
b101 /
1#
#1150000
0#
#1160000
b110 /
1#
#1170000
0#
#1180000
b111 /
1#
#1190000
0#
#1200000
b1000 /
15
1#
1!
#1210000
0#
#1220000
14
b1001 /
1#
#1230000
0#
#1240000
b0 /
13
1#
#1250000
0#
#1260000
12
b1 /
1#
#1270000
0#
#1280000
b10 /
1#
#1290000
0#
#1300000
b11 /
1#
#1310000
0#
#1320000
b100 /
1#
#1330000
0#
#1340000
b101 6
b10101 &
b10101 0
b10101 8
b101 /
1#
#1350000
0#
#1360000
b110 /
b10101 @
1#
#1370000
0#
#1380000
b111 /
1#
#1390000
0#
#1400000
b1000 /
05
1#
0!
#1410000
0#
#1420000
1'
04
b1001 /
1#
#1430000
0#
#1440000
0'
b0 /
03
1#
#1450000
0#
#1460000
02
b1 /
1#
#1470000
0#
#1480000
b10 /
1#
#1490000
0#
#1500000
b11 /
1#
#1510000
0#
#1520000
b100 /
1#
#1530000
0#
#1540000
b110 6
b101 /
1#
#1550000
0#
#1560000
b110 /
1#
#1570000
0#
#1580000
b111 /
1#
#1590000
0#
#1600000
b1000 /
15
1#
1!
#1610000
0#
#1620000
14
b1001 /
1#
#1630000
0#
#1640000
b0 /
13
1#
#1650000
0#
#1660000
12
b1 /
1#
#1670000
0#
#1680000
b10 /
1#
#1690000
0#
#1700000
b11 /
1#
#1710000
0#
#1720000
b100 /
1#
#1730000
0#
#1740000
b111 6
b1010101 &
b1010101 0
b1010101 8
b101 /
1#
#1750000
0#
#1760000
b110 /
b1010101 @
1#
#1770000
0#
#1780000
b111 /
1#
#1790000
0#
#1800000
b1000 /
05
1#
0!
#1810000
0#
#1820000
1'
04
b1001 /
1#
#1830000
0#
#1840000
0'
b0 /
03
1#
#1850000
0#
#1860000
02
b1 /
1#
#1870000
0#
#1880000
b10 /
1#
#1890000
0#
#1900000
b11 /
1#
#1910000
0#
#1920000
b100 /
1#
#1930000
0#
#1940000
b1000 7
b101 /
1#
#1950000
0#
#1960000
b110 /
1#
#1970000
0#
#1980000
b111 /
1#
#1990000
0#
#2000000
b1000 /
15
1#
1!
#2010000
0#
#2020000
14
b1001 /
1#
#2030000
0#
#2040000
b0 /
13
1#
#2050000
0#
#2060000
12
b1 /
1#
#2070000
0#
#2080000
b10 /
1#
#2090000
0#
#2100000
b11 /
1#
#2110000
0#
#2120000
b100 /
1#
#2130000
0#
#2140000
b10000 7
b101 /
1#
#2150000
0#
#2160000
b110 /
b1 7
1%
01
1#
#2170000
0#
#2180000
b10 B
1A
0%
b0 6
b0 /
1#
#2190000
0#
#2200000
b1 ?
0"
1#
#2210000
0#
#2220000
b10 ?
1#
#2230000
0#
#2240000
b11 ?
1#
#2250000
0#
#2260000
b100 ?
1#
#2270000
0#
#2280000
b101 ?
1#
#2290000
0#
#2300000
b110 ?
1#
#2310000
0#
#2320000
b111 ?
1#
#2330000
0#
#2340000
b1000 ?
1#
#2350000
0#
#2360000
b1001 ?
1#
#2370000
0#
#2380000
b100 B
b0 ?
1#
#2390000
0#
#2400000
b1 ?
1"
1#
#2410000
0#
#2420000
b10 ?
1#
#2430000
0#
#2440000
b11 ?
1#
#2450000
0#
#2460000
b100 ?
1#
#2470000
0#
#2480000
b101 ?
1#
#2490000
0#
#2500000
b110 ?
1#
b1 E
#2510000
0#
#2520000
b111 ?
1#
#2530000
0#
#2540000
b1000 ?
1#
#2550000
0#
#2560000
b1001 ?
1#
#2570000
0#
#2580000
b1 C
b0 ?
1#
#2590000
0#
#2600000
b1 ?
0"
1#
#2610000
0#
#2620000
b10 ?
1#
#2630000
0#
#2640000
b11 ?
1#
#2650000
0#
#2660000
b100 ?
1#
#2670000
0#
#2680000
b101 ?
1#
#2690000
0#
#2700000
b110 ?
1#
#2710000
0#
#2720000
b111 ?
1#
#2730000
0#
#2740000
b1000 ?
1#
#2750000
0#
#2760000
b1001 ?
1#
#2770000
0#
#2780000
b10 C
b0 ?
1#
#2790000
0#
#2800000
b1 ?
1"
1#
#2810000
0#
#2820000
b10 ?
1#
#2830000
0#
#2840000
b11 ?
1#
#2850000
0#
#2860000
b100 ?
1#
#2870000
0#
#2880000
b101 ?
1#
#2890000
0#
#2900000
b110 ?
1#
b101 E
#2910000
0#
#2920000
b111 ?
1#
#2930000
0#
#2940000
b1000 ?
1#
#2950000
0#
#2960000
b1001 ?
1#
#2970000
0#
#2980000
b11 C
b0 ?
1#
#2990000
0#
#3000000
b1 ?
0"
1#
#3010000
0#
#3020000
b10 ?
1#
#3030000
0#
#3040000
b11 ?
1#
#3050000
0#
#3060000
b100 ?
1#
#3070000
0#
#3080000
b101 ?
1#
#3090000
0#
#3100000
b110 ?
1#
#3110000
0#
#3120000
b111 ?
1#
#3130000
0#
#3140000
b1000 ?
1#
#3150000
0#
#3160000
b1001 ?
1#
#3170000
0#
#3180000
b100 C
b0 ?
1#
#3190000
0#
#3200000
b1 ?
1"
1#
#3210000
0#
#3220000
b10 ?
1#
#3230000
0#
#3240000
b11 ?
1#
#3250000
0#
#3260000
b100 ?
1#
#3270000
0#
#3280000
b101 ?
1#
#3290000
0#
#3300000
b110 ?
1#
b10101 E
#3310000
0#
#3320000
b111 ?
1#
#3330000
0#
#3340000
b1000 ?
1#
#3350000
0#
#3360000
b1001 ?
1#
#3370000
0#
#3380000
b101 C
b0 ?
1#
#3390000
0#
#3400000
b1 ?
0"
1#
#3410000
0#
#3420000
b10 ?
1#
#3430000
0#
#3440000
b11 ?
1#
#3450000
0#
#3460000
b100 ?
1#
#3470000
0#
#3480000
b101 ?
1#
#3490000
0#
#3500000
b110 ?
1#
#3510000
0#
#3520000
b111 ?
1#
#3530000
0#
#3540000
b1000 ?
1#
#3550000
0#
#3560000
b1001 ?
1#
#3570000
0#
#3580000
b110 C
b0 ?
1#
#3590000
0#
#3600000
b1 ?
1"
1#
#3610000
0#
#3620000
b10 ?
1#
#3630000
0#
#3640000
b11 ?
1#
#3650000
0#
#3660000
b100 ?
1#
#3670000
0#
#3680000
b101 ?
1#
#3690000
0#
#3700000
b110 ?
1#
b1010101 E
#3710000
0#
#3720000
b111 ?
1#
#3730000
0#
#3740000
b1000 ?
1#
#3750000
0#
#3760000
b1001 ?
1#
#3770000
0#
#3780000
b111 C
b0 ?
1#
#3790000
0#
#3800000
b1 ?
0"
1#
#3810000
0#
#3820000
b10 ?
1#
#3830000
0#
#3840000
b11 ?
1#
#3850000
0#
#3860000
b100 ?
1#
#3870000
0#
#3880000
b101 ?
1#
#3890000
0#
#3900000
b110 ?
1#
#3910000
0#
#3920000
b111 ?
1#
#3930000
0#
#3940000
b1000 ?
1#
#3950000
0#
#3960000
b1001 ?
1#
#3970000
0#
#3980000
b1000 B
b0 ?
1#
#3990000
0#
#4000000
b1 ?
1"
1#
#4010000
0#
#4020000
b10 ?
1#
#4030000
0#
#4040000
b11 ?
1#
#4050000
0#
#4060000
b100 ?
1#
#4070000
0#
#4080000
b101 ?
1#
#4090000
0#
#4100000
b110 ?
1#
1H
#4110000
0#
#4120000
b111 ?
1#
#4130000
0#
#4140000
b1000 ?
1#
#4150000
0#
#4160000
b1001 ?
1#
#4170000
0#
#4180000
b10000 B
b0 ?
1#
#4190000
0#
#4200000
b1 ?
b1 B
1D
0A
1#
#4210000
0#
#4220000
0D
b0 C
b0 ?
1#
#4230000
0#
#4240000
1#
#4250000
0#
#4260000
1#
#4270000
0#
#4280000
1#
#4290000
0#
#4300000
1#
1F
